onegov.people-0.11.1-py3.6-nspkg.pth
onegov/people/.gitignore
onegov/people/__init__.py
onegov/people/upgrade.py
onegov/people/collections/__init__.py
onegov/people/collections/agencies.py
onegov/people/collections/memberships.py
onegov/people/collections/people.py
onegov/people/models/__init__.py
onegov/people/models/agency.py
onegov/people/models/membership.py
onegov/people/models/person.py
onegov/people/tests/conftest.py
onegov/people/tests/test_collections.py
onegov/people/tests/test_models.py
onegov/people/tests/fixtures/organigram.jpg
onegov/people/tests/fixtures/organigram.png
onegov.people-0.11.1.dist-info/METADATA
onegov.people-0.11.1.dist-info/WHEEL
onegov.people-0.11.1.dist-info/entry_points.txt
onegov.people-0.11.1.dist-info/namespace_packages.txt
onegov.people-0.11.1.dist-info/top_level.txt
onegov.people-0.11.1.dist-info/RECORD
