Metadata-Version: 2.1
Name: onegov.people
Version: 0.11.1
Summary: People for OneGov.
Home-page: http://github.com/OneGov/onegov.people
Author: Seantis GmbH
Author-email: info@seantis.ch
License: GPLv2
Platform: any
Classifier: Intended Audience :: Developers
Classifier: Programming Language :: Python :: 3 :: Only
Classifier: Programming Language :: Python :: 3.6
Classifier: Programming Language :: Python :: 3.7
Classifier: Topic :: Software Development :: Libraries :: Python Modules
Classifier: License :: OSI Approved :: GNU General Public License v2 (GPLv2)
Requires-Python: >=3.6
Requires-Dist: onegov.core (>=0.74.3)
Requires-Dist: onegov.file
Requires-Dist: onegov.search (>=1.1.0)
Requires-Dist: vobject
Provides-Extra: test
Requires-Dist: coverage ; extra == 'test'
Requires-Dist: onegov-testing ; extra == 'test'
Requires-Dist: pytest ; extra == 'test'
